<?xml version="1.0" encoding="UTF-8"?><database>
    <element db_object_id="e5fd49a81b1b1dd427967449cc4bcb92" label="Answer Choice" max_length="40" name="x_autg_kbb_secret_answer_choice" type="collection">
        <element calculation="(function calculatedFieldValue(current) {&#13;&#10;&#13;&#10;&#9;// Add your code here&#13;&#10;&#9;return '';  // return the calculated value&#13;&#10;&#13;&#10;})(current);" label="Active" max_length="40" name="active" type="boolean"/>
        <element calculation="(function calculatedFieldValue(current) {&#13;&#10;&#13;&#10;&#9;// Add your code here&#13;&#10;&#9;return '';  // return the calculated value&#13;&#10;&#13;&#10;})(current);" display="true" label="Choice" max_length="40" name="choice" type="string"/>
        <element calculation="(function calculatedFieldValue(current) {&#13;&#10;&#13;&#10;&#9;// Add your code here&#13;&#10;&#9;return '';  // return the calculated value&#13;&#10;&#13;&#10;})(current);" choice="1" label="Dependent Value" max_length="40" name="dependent_value" type="string">
            <choice>
                <element inactive_on_update="false" label="Range" sequence="10" value="Range"/>
                <element inactive_on_update="false" label="Sub Total" sequence="20" value="Sub Total"/>
                <element inactive_on_update="false" label="Yes/No" sequence="30" value="Yes/No"/>
            </choice>
        </element>
        <element calculation="(function calculatedFieldValue(current) {&#13;&#10;&#13;&#10;&#9;// Add your code here&#13;&#10;&#9;return '';  // return the calculated value&#13;&#10;&#13;&#10;})(current);" choice="1" label="Element" max_length="40" name="element" type="string">
            <choice>
                <element inactive_on_update="false" label="Answer" sequence="1" value="Answer"/>
                <element inactive_on_update="false" label="Type" sequence="2" value="Type"/>
                <element inactive_on_update="false" label="State" sequence="3" value="State"/>
                <element inactive_on_update="false" label="Final Score Formula" sequence="4" value="Final Score Formula"/>
                <element inactive_on_update="false" label="Category" sequence="5" value="Category"/>
            </choice>
        </element>
        <element attributes="ignore_filter_on_new=true" default="javascript:global.getNextObjNumberPadded();" label="Number" max_length="40" name="number" read_only="true" type="string"/>
        <element calculation="(function calculatedFieldValue(current) {&#13;&#10;&#13;&#10;&#9;// Add your code here&#13;&#10;&#9;return '';  // return the calculated value&#13;&#10;&#13;&#10;})(current);" label="Order" max_length="40" name="order" type="integer"/>
        <element calculation="(function calculatedFieldValue(current) {&#13;&#10;&#13;&#10;&#9;// Add your code here&#13;&#10;&#9;return '';  // return the calculated value&#13;&#10;&#13;&#10;})(current);" choice="1" label="Table" max_length="100" name="table" type="string">
            <choice>
                <element inactive_on_update="false" label="Answers" sequence="1" value="x_autg_kbb_secret_answers"/>
                <element inactive_on_update="false" label="Questions" sequence="2" value="x_autg_kbb_secret_questions"/>
                <element inactive_on_update="false" label="Scorecard" sequence="3" value="x_autg_kbb_secret_scorecards"/>
                <element inactive_on_update="false" label="Template" sequence="4" value="x_autg_kbb_secret_templates"/>
            </choice>
        </element>
    </element>
</database>
